konic/__init__.py
konic/agent/__init__.py
konic/agent/agent.py
konic/agent/base.py
konic/callback/__init__.py
konic/callback/base.py
konic/callback/callback.py
konic/callback/decorators.py
konic/callback/enums.py
konic/callback/utils.py
konic/cli/__init__.py
konic/cli/decorators.py
konic/cli/enums.py
konic/cli/env_keys.py
konic/cli/root.py
konic/cli/utils.py
konic/cli/boilerplates/basic/cookiecutter.json
"konic/cli/boilerplates/basic/{{cookiecutter.name.replace("" "", ""-"").lower()}}/agent.py"
konic/cli/boilerplates/callback/cookiecutter.json
"konic/cli/boilerplates/callback/{{cookiecutter.name.replace("" "", ""-"").lower()}}/agent.py"
konic/cli/boilerplates/csv_streamer/cookiecutter.json
"konic/cli/boilerplates/csv_streamer/{{cookiecutter.name.replace("" "", ""-"").lower()}}/agent.py"
konic/cli/boilerplates/custom/cookiecutter.json
"konic/cli/boilerplates/custom/{{cookiecutter.name.replace("" "", ""-"").lower()}}/agent.py"
konic/cli/boilerplates/finetuning_advanced/cookiecutter.json
"konic/cli/boilerplates/finetuning_advanced/{{cookiecutter.name.replace("" "", ""-"").lower()}}/agent.py"
konic/cli/boilerplates/finetuning_basic/cookiecutter.json
"konic/cli/boilerplates/finetuning_basic/{{cookiecutter.name.replace("" "", ""-"").lower()}}/agent.py"
konic/cli/boilerplates/full/cookiecutter.json
"konic/cli/boilerplates/full/{{cookiecutter.name.replace("" "", ""-"").lower()}}/agent.py"
konic/cli/client/__init__.py
konic/cli/client/api_client.py
konic/cli/src/__init__.py
konic/cli/src/agents.py
konic/cli/src/artifacts.py
konic/cli/src/data.py
konic/cli/src/health.py
konic/cli/src/inference.py
konic/cli/src/models.py
konic/cli/src/training.py
konic/common/__init__.py
konic/common/errors/__init__.py
konic/common/errors/base.py
konic/common/errors/cli.py
konic/engine/__init__.py
konic/engine/train.py
konic/engine/utils.py
konic/environment/__init__.py
konic/environment/base.py
konic/environment/core.py
konic/environment/environments.py
konic/environment/reward/__init__.py
konic-0.1.23.dist-info/METADATA
konic-0.1.23.dist-info/WHEEL
konic-0.1.23.dist-info/entry_points.txt
konic-0.1.23.dist-info/RECORD
