Metadata-Version: 2.4
Name: konic
Version: 0.1.23
Summary: Official Konic Agent Development Toolkit
Author-email: Ege Sabanci <ege@konic.io>
Requires-Python: >=3.12
Requires-Dist: accelerate>=1.12.0
Requires-Dist: cookiecutter>=2.6.0
Requires-Dist: datasets>=4.4.2
Requires-Dist: httpx>=0.28.1
Requires-Dist: pandas>=2.3.3
Requires-Dist: peft>=0.18.0
Requires-Dist: pydantic>=2.11.10
Requires-Dist: python-dotenv>=1.2.1
Requires-Dist: ray[default,rllib]>=2.51.1
Requires-Dist: rich>=13.0.0
Requires-Dist: torch>=2.9.0
Requires-Dist: transformers>=4.57.3
Requires-Dist: trl>=0.26.2
Requires-Dist: typer>=0.20.0
